{
 "key": "dart_20260703000467",
 "created_at": "2026-07-05T09:12:31.545991+00:00",
 "category": "EARNINGS",
 "entity": "넥스트아이",
 "period": "2025-4Q",
 "title": "넥스트아이 2025-4Q 실적 공시",
 "anchors": [
  {
   "entity": "넥스트아이",
   "metric": "매출액",
   "value": 57.7,
   "unit": "억원",
   "period": "2025-11013",
   "source": "DART",
   "prev": null
  },
  {
   "entity": "넥스트아이",
   "metric": "영업이익",
   "value": -17.8,
   "unit": "억원",
   "period": "2025-11013",
   "source": "DART",
   "prev": null
  }
 ],
 "timeline": {
  "kind": "official",
  "title": "넥스트아이 [기재정정]사업보고서 (2025.12)",
  "source": "DART",
  "url": "https://dart.fss.or.kr/dsaf001/main.do?rcpNo=20260703000467"
 }
}