{
 "id": "c9935a100fd7ce01f",
 "title": "미국 관세",
 "one_liner": "트럼프가 새로운 관세를 부과하려고 해요.",
 "why_now": "관세가 부과되면 수입품의 가격이 오를 수 있어요.",
 "impact_line": "주류의 가격이 오를 수 있어요",
 "raw_title": "Dodgers split doubleheader with Yankees after long day in Bronx",
 "category": "GEO",
 "status": "active",
 "origin": "cluster",
 "sources": 13,
 "importance": 85,
 "last_update": "2026-07-21T23:16:54.417467+00:00",
 "event_at": "2026-07-21T22:00:00+00:00",
 "has_visual": false,
 "headline_stat": null,
 "spark": null,
 "icon": "🌍",
 "details": [
  "트럼프가 새로운 관세를 부과하려고 해요.",
  "캐나다의 온타리오와 퀘벡이 미국 주류를 팔기 좋은 기회를 얻었어요.",
  "트럼프의 고문들이 더 많은 관세를 부과하지 말라고 말리고 있어요.",
  "GM이 새로운 가스엔진 캐딜락 모델을 출시할 계획이에요."
 ],
 "effects": [
  "수입품의 가격이 오르면 소비자가 부담이 늘 수 있어요!",
  "新的 관세가 부과되면 국제 무역이 어려워질 수 있어요!"
 ],
 "model": "llama-3.3-70b-versatile",
 "visual": null,
 "anchors": [],
 "headlines": [
  {
   "title": "investingLive Americas FX news wrap 21 Jul : USDJPY trades to a 40 year high and runs",
   "source": "investinglive.com",
   "url": "https://investinglive.com:443/news/investinglive-americas-fx-news-wrap-21-jul-usdjpy-trades-to-a-40-year-high-and-runs",
   "published_at": "2026-07-21T22:00:00+00:00",
   "lang": "en"
  },
  {
   "title": "Hasbro Gets a Big Bump From Magic : The Gathering",
   "source": "newser.com",
   "url": "https://www.newser.com/story/393246/hasbro-gets-a-big-bump-from-magic-the-gathering.html",
   "published_at": "2026-07-21T22:00:00+00:00",
   "lang": "en"
  },
  {
   "title": "Trump new tariffs give Ontario and Quebec the perfect excuse to sell their unsold American booze",
   "source": "torontotelegraph.com",
   "url": "http://www.torontotelegraph.com/news/279201939/trump-new-tariffs-give-ontario-and-quebec-the-perfect-excuse-to-sell-their-unsold-american-booze",
   "published_at": "2026-07-21T22:00:00+00:00",
   "lang": "en"
  },
  {
   "title": "GM To Launch New Gas - Powered Cadillac Models As EV Strategy Shifts",
   "source": "finanznachrichten.de",
   "url": "https://www.finanznachrichten.de/nachrichten-2026-07/69086862-gm-to-launch-new-gas-powered-cadillac-models-as-ev-strategy-shifts-020.htm",
   "published_at": "2026-07-21T22:00:00+00:00",
   "lang": "en"
  },
  {
   "title": "Prediction : This Dividend ETF Yield Wont Stay Under 3 . 5 % for Long",
   "source": "fool.com",
   "url": "https://www.fool.com/investing/2026/07/21/predict-dividend-etf-schd-yield-wont-stay-under/?source=iedfolrf0000001",
   "published_at": "2026-07-21T21:45:00+00:00",
   "lang": "en"
  },
  {
   "title": "Trump Advisers Scramble to Talk Him Out of More Disastrous Tariffs",
   "source": "newrepublic.com",
   "url": "https://newrepublic.com/post/213341/dopnald-trump-advisers-talk-out-disastrous-tariffs",
   "published_at": "2026-07-21T21:45:00+00:00",
   "lang": "en"
  },
  {
   "title": "Speedway prepares for two - night Prairie Modified Nationals this weekend - DiscoverEstevan . com - Local news , Weather , Sports , Free Classifieds and Business Listings for the Estevan , Saskatchewan",
   "source": "discoverestevan.com",
   "url": "https://discoverestevan.com/articles/speedway-prepares-for-two-night-prairie-modified-nationals-this-weekend",
   "published_at": "2026-07-21T20:45:00+00:00",
   "lang": "en"
  },
  {
   "title": "The Touring Motorcycle That Feels Smaller Than It Really Is",
   "source": "topspeed.com",
   "url": "https://www.topspeed.com/touring-motorcycle-feels-smaller-than-it-really-is/",
   "published_at": "2026-07-21T17:30:00+00:00",
   "lang": "en"
  },
  {
   "title": "I Drove Jeep First Proper Hybrid . It Feels More Like A Toyota",
   "source": "insideevs.com",
   "url": "https://insideevs.com:443/reviews/802028/2026-jeep-cherokee-hybrid-review-toyota-suv/",
   "published_at": "2026-07-21T17:30:00+00:00",
   "lang": "en"
  },
  {
   "title": "The Red Chickz Doubles Down on Texas with Carrollton Grand Opening",
   "source": "prnewswire.com",
   "url": "http://www.prnewswire.com/news-releases/the-red-chickz-doubles-down-on-texas-with-carrollton-grand-opening-302830177.html",
   "published_at": "2026-07-21T11:45:00+00:00",
   "lang": "en"
  }
 ],
 "timeline": [
  {
   "kind": "headline",
   "title": "investingLive Americas FX news wrap 21 Jul : USDJPY trades to a 40 year high and runs",
   "source": "investinglive.com",
   "url": "https://investinglive.com:443/news/investinglive-americas-fx-news-wrap-21-jul-usdjpy-trades-to-a-40-year-high-and-runs",
   "at": "2026-07-21T22:00:00+00:00"
  },
  {
   "kind": "headline",
   "title": "Hasbro Gets a Big Bump From Magic : The Gathering",
   "source": "newser.com",
   "url": "https://www.newser.com/story/393246/hasbro-gets-a-big-bump-from-magic-the-gathering.html",
   "at": "2026-07-21T22:00:00+00:00"
  },
  {
   "kind": "headline",
   "title": "Trump tariffs on northern neighbor fall flat in US :  Not a huge fan",
   "source": "wjla.com",
   "url": "https://wjla.com/news/nation-world/president-trumps-tariffs-on-northern-neighbor-canada-fall-flat-in-us-not-a-huge-fan-economy-taxes",
   "at": "2026-07-21T22:00:00+00:00"
  },
  {
   "kind": "headline",
   "title": "Trump tariffs on northern neighbor fall flat in US :  Not a huge fan",
   "source": "cbs12.com",
   "url": "https://cbs12.com/news/nation-world/president-trumps-tariffs-on-northern-neighbor-canada-fall-flat-in-us-not-a-huge-fan-economy-taxes",
   "at": "2026-07-21T22:00:00+00:00"
  },
  {
   "kind": "headline",
   "title": "Trump new tariffs give Ontario and Quebec the perfect excuse to sell their unsold American booze",
   "source": "torontotelegraph.com",
   "url": "http://www.torontotelegraph.com/news/279201939/trump-new-tariffs-give-ontario-and-quebec-the-perfect-excuse-to-sell-their-unsold-american-booze",
   "at": "2026-07-21T22:00:00+00:00"
  },
  {
   "kind": "headline",
   "title": "Dow Jones jumps 386 points as global stocks take off",
   "source": "vietnamtribune.com",
   "url": "http://www.vietnamtribune.com/news/279201899/dow-jones-jumps-386-points-as-global-stocks-take-off",
   "at": "2026-07-21T22:00:00+00:00"
  },
  {
   "kind": "headline",
   "title": "Dow Jones jumps 386 points as global stocks take off",
   "source": "taiwansun.com",
   "url": "http://www.taiwansun.com/news/279201899/dow-jones-jumps-386-points-as-global-stocks-take-off",
   "at": "2026-07-21T22:00:00+00:00"
  },
  {
   "kind": "headline",
   "title": "Dow Jones jumps 386 points as global stocks take off",
   "source": "baltimorestar.com",
   "url": "http://www.baltimorestar.com/news/279201899/dow-jones-jumps-386-points-as-global-stocks-take-off",
   "at": "2026-07-21T22:00:00+00:00"
  },
  {
   "kind": "headline",
   "title": "Dow Jones jumps 386 points as global stocks take off",
   "source": "utahindependent.com",
   "url": "http://www.utahindependent.com/news/279201899/dow-jones-jumps-386-points-as-global-stocks-take-off",
   "at": "2026-07-21T22:00:00+00:00"
  },
  {
   "kind": "headline",
   "title": "Dow Jones jumps 386 points as global stocks take off",
   "source": "tennesseedaily.com",
   "url": "http://www.tennesseedaily.com/news/279201899/dow-jones-jumps-386-points-as-global-stocks-take-off",
   "at": "2026-07-21T22:00:00+00:00"
  },
  {
   "kind": "headline",
   "title": "Prediction : This Dividend ETF Yield Wont Stay Under 3 . 5 % for Long",
   "source": "finance.yahoo.com",
   "url": "https://finance.yahoo.com/markets/stocks/articles/prediction-dividend-etfs-yield-wont-212500563.html",
   "at": "2026-07-21T22:00:00+00:00"
  },
  {
   "kind": "headline",
   "title": "GM To Launch New Gas - Powered Cadillac Models As EV Strategy Shifts",
   "source": "finanznachrichten.de",
   "url": "https://www.finanznachrichten.de/nachrichten-2026-07/69086862-gm-to-launch-new-gas-powered-cadillac-models-as-ev-strategy-shifts-020.htm",
   "at": "2026-07-21T22:00:00+00:00"
  },
  {
   "kind": "headline",
   "title": "Trump tariffs on northern neighbor fall flat in US :  Not a huge fan",
   "source": "krcgtv.com",
   "url": "https://krcgtv.com/news/nation-world/president-trumps-tariffs-on-northern-neighbor-canada-fall-flat-in-us-not-a-huge-fan-economy-taxes",
   "at": "2026-07-21T22:00:00+00:00"
  },
  {
   "kind": "headline",
   "title": "Prediction : This Dividend ETF Yield Wont Stay Under 3 . 5 % for Long",
   "source": "fool.com",
   "url": "https://www.fool.com/investing/2026/07/21/predict-dividend-etf-schd-yield-wont-stay-under/?source=iedfolrf0000001",
   "at": "2026-07-21T21:45:00+00:00"
  },
  {
   "kind": "headline",
   "title": "Trump Advisers Scramble to Talk Him Out of More Disastrous Tariffs",
   "source": "newrepublic.com",
   "url": "https://newrepublic.com/post/213341/dopnald-trump-advisers-talk-out-disastrous-tariffs",
   "at": "2026-07-21T21:45:00+00:00"
  },
  {
   "kind": "headline",
   "title": "Dow Jones jumps 386 points as global stocks take off",
   "source": "chinanationalnews.com",
   "url": "http://www.chinanationalnews.com/news/279201899/dow-jones-jumps-386-points-as-global-stocks-take-off",
   "at": "2026-07-21T21:45:00+00:00"
  },
  {
   "kind": "headline",
   "title": "Dow Jones jumps 386 points as global stocks take off",
   "source": "massachusettssun.com",
   "url": "http://www.massachusettssun.com/news/279201899/dow-jones-jumps-386-points-as-global-stocks-take-off",
   "at": "2026-07-21T21:45:00+00:00"
  },
  {
   "kind": "headline",
   "title": "Dow Jones jumps 386 points as global stocks take off",
   "source": "jamaicantimes.com",
   "url": "http://www.jamaicantimes.com/news/279201899/dow-jones-jumps-386-points-as-global-stocks-take-off",
   "at": "2026-07-21T21:45:00+00:00"
  },
  {
   "kind": "headline",
   "title": "Wall Street marches sharply higher as buyers climb back on board",
   "source": "azerbaijannews.net",
   "url": "http://www.azerbaijannews.net/news/279201899/wall-street-marches-sharply-higher-as-buyers-climb-back-on-board",
   "at": "2026-07-21T21:45:00+00:00"
  },
  {
   "kind": "headline",
   "title": "Dow Jones jumps 386 points as global stocks take off",
   "source": "europesun.com",
   "url": "http://www.europesun.com/news/279201899/dow-jones-jumps-386-points-as-global-stocks-take-off",
   "at": "2026-07-21T21:45:00+00:00"
  },
  {
   "kind": "headline",
   "title": "Trump tariffs on northern neighbor fall flat in US :  Not a huge fan",
   "source": "foxrochester.com",
   "url": "https://foxrochester.com/news/nation-world/president-trumps-tariffs-on-northern-neighbor-canada-fall-flat-in-us-not-a-huge-fan-economy-taxes",
   "at": "2026-07-21T21:45:00+00:00"
  },
  {
   "kind": "headline",
   "title": "Trump tariffs on northern neighbor fall flat in US :  Not a huge fan",
   "source": "abc7amarillo.com",
   "url": "https://abc7amarillo.com/news/nation-world/president-trumps-tariffs-on-northern-neighbor-canada-fall-flat-in-us-not-a-huge-fan-economy-taxes",
   "at": "2026-07-21T21:45:00+00:00"
  },
  {
   "kind": "headline",
   "title": "Speedway prepares for two - night Prairie Modified Nationals this weekend - DiscoverEstevan . com - Local news , Weather , Sports , Free Classifieds and Business Listings for the Estevan , Saskatchewan",
   "source": "discoverestevan.com",
   "url": "https://discoverestevan.com/articles/speedway-prepares-for-two-night-prairie-modified-nationals-this-weekend",
   "at": "2026-07-21T20:45:00+00:00"
  },
  {
   "kind": "headline",
   "title": "The Touring Motorcycle That Feels Smaller Than It Really Is",
   "source": "topspeed.com",
   "url": "https://www.topspeed.com/touring-motorcycle-feels-smaller-than-it-really-is/",
   "at": "2026-07-21T17:30:00+00:00"
  },
  {
   "kind": "headline",
   "title": "I Drove Jeep First Proper Hybrid . It Feels More Like A Toyota",
   "source": "insideevs.com",
   "url": "https://insideevs.com:443/reviews/802028/2026-jeep-cherokee-hybrid-review-toyota-suv/",
   "at": "2026-07-21T17:30:00+00:00"
  },
  {
   "kind": "headline",
   "title": "The Red Chickz Doubles Down on Texas with Carrollton Grand Opening",
   "source": "prnewswire.com",
   "url": "http://www.prnewswire.com/news-releases/the-red-chickz-doubles-down-on-texas-with-carrollton-grand-opening-302830177.html",
   "at": "2026-07-21T11:45:00+00:00"
  },
  {
   "kind": "headline",
   "title": "Dodgers split doubleheader with Yankees after long day in Bronx",
   "source": "sgvtribune.com",
   "url": "https://www.sgvtribune.com/2026/07/19/dodgers-split-doubleheader-with-yankees-after-long-day-in-bronx/",
   "at": "2026-07-20T08:00:00+00:00"
  },
  {
   "kind": "headline",
   "title": "Dodgers split doubleheader with Yankees after long day in Bronx",
   "source": "presstelegram.com",
   "url": "https://www.presstelegram.com/2026/07/19/dodgers-split-doubleheader-with-yankees-after-long-day-in-bronx/",
   "at": "2026-07-20T07:45:00+00:00"
  },
  {
   "kind": "headline",
   "title": "JD Vance picks a lane and a fight",
   "source": "washingtonexaminer.com",
   "url": "https://www.washingtonexaminer.com/in_focus/4654550/jd-vance-picks-a-lane-and-a-fight/",
   "at": "2026-07-19T21:45:00+00:00"
  },
  {
   "kind": "headline",
   "title": "Dodgers take first game of doubleheader behind dominant Yoshinobu Yamamoto",
   "source": "whittierdailynews.com",
   "url": "https://www.whittierdailynews.com/2026/07/19/dodgers-take-first-game-of-doubleheader-behind-dominant-yoshinobu-yamamoto/",
   "at": "2026-07-19T21:45:00+00:00"
  }
 ],
 "glossary": [
  {
   "term": "관세",
   "easy": "수입 물건에 매기는 세금이에요.",
   "example": "오르면 그 물건 값이 비싸지기 쉬워요."
  }
 ],
 "related": [
  {
   "id": "ca7e18652a27e4c6f",
   "title": "Left - leaning group says state faces affordability crisis",
   "category": "GEO",
   "shared": []
  },
  {
   "id": "c7f9a22157d5febb4",
   "title": "EU forces Google to share search data and open Android to rival AI companies",
   "category": "GEO",
   "shared": []
  },
  {
   "id": "c6f9e57edbc5d69b6",
   "title": "Could The US - Iran Battle For Hormuz Be A Win For Russia And China",
   "category": "GEO",
   "shared": []
  },
  {
   "id": "ca5c88b2eecf2f428",
   "title": "Why is it so hard for the U . S . to win wars ?",
   "category": "GEO",
   "shared": []
  },
  {
   "id": "cd2c26bf163eba3ef",
   "title": "Ireland narrowly misses record - matching heatwave",
   "category": "GEO",
   "shared": []
  }
 ],
 "created_at": "2026-07-20T11:19:05.717119+00:00"
}